contasOrama/admin.py
contasOrama/apps.py
contasOrama/models.py
contasOrama/pagination.py
contasOrama/permissions.py
contasOrama/serializers.py
contasOrama/tests.py
contasOrama/urls.py
contasOrama/views.py
contasOrama/__init__.py
contasOrama/migrations/0001_initial.py
contasOrama/migrations/__init__.py
contasOrama-0.0.1.dist-info/DESCRIPTION.rst
contasOrama-0.0.1.dist-info/METADATA
contasOrama-0.0.1.dist-info/metadata.json
contasOrama-0.0.1.dist-info/RECORD
contasOrama-0.0.1.dist-info/top_level.txt
contasOrama-0.0.1.dist-info/WHEEL
